tensorflow_metadata/__init__.py
tensorflow_metadata/version.py
tensorflow_metadata/proto/__init__.py
tensorflow_metadata/proto/v0/__init__.py
tensorflow_metadata/proto/v0/anomalies_pb2.py
tensorflow_metadata/proto/v0/derived_feature_pb2.py
tensorflow_metadata/proto/v0/metric_pb2.py
tensorflow_metadata/proto/v0/path_pb2.py
tensorflow_metadata/proto/v0/problem_statement_pb2.py
tensorflow_metadata/proto/v0/schema_pb2.py
tensorflow_metadata/proto/v0/statistics_pb2.py
tensorflow_metadata-1.17.2.dist-info/licenses/LICENSE
tensorflow_metadata-1.17.2.dist-info/METADATA
tensorflow_metadata-1.17.2.dist-info/WHEEL
tensorflow_metadata-1.17.2.dist-info/namespace_packages.txt
tensorflow_metadata-1.17.2.dist-info/top_level.txt
tensorflow_metadata-1.17.2.dist-info/RECORD
